mpqp/__init__.py
mpqp/all.py
mpqp/core/__init__.py
mpqp/core/circuit.py
mpqp/core/languages.py
mpqp/core/instruction/__init__.py
mpqp/core/instruction/barrier.py
mpqp/core/instruction/breakpoint.py
mpqp/core/instruction/instruction.py
mpqp/core/instruction/gates/__init__.py
mpqp/core/instruction/gates/controlled_gate.py
mpqp/core/instruction/gates/custom_controlled_gate.py
mpqp/core/instruction/gates/custom_gate.py
mpqp/core/instruction/gates/gate.py
mpqp/core/instruction/gates/gate_definition.py
mpqp/core/instruction/gates/native_gates.py
mpqp/core/instruction/gates/parametrized_gate.py
mpqp/core/instruction/measurement/__init__.py
mpqp/core/instruction/measurement/basis.py
mpqp/core/instruction/measurement/basis_measure.py
mpqp/core/instruction/measurement/expectation_value.py
mpqp/core/instruction/measurement/measure.py
mpqp/core/instruction/measurement/pauli_string.py
mpqp/execution/__init__.py
mpqp/execution/devices.py
mpqp/execution/job.py
mpqp/execution/remote_handler.py
mpqp/execution/result.py
mpqp/execution/runner.py
mpqp/execution/simulated_devices.py
mpqp/execution/connection/__init__.py
mpqp/execution/connection/aws_connection.py
mpqp/execution/connection/azure_connection.py
mpqp/execution/connection/env_manager.py
mpqp/execution/connection/google_connection.py
mpqp/execution/connection/ibm_connection.py
mpqp/execution/connection/ionq_connection.py
mpqp/execution/connection/qlm_connection.py
mpqp/execution/providers/__init__.py
mpqp/execution/providers/atos.py
mpqp/execution/providers/aws.py
mpqp/execution/providers/azure.py
mpqp/execution/providers/google.py
mpqp/execution/providers/ibm.py
mpqp/execution/vqa/__init__.py
mpqp/execution/vqa/optimizer.py
mpqp/execution/vqa/qaoa.py
mpqp/execution/vqa/qubo.py
mpqp/execution/vqa/vqa.py
mpqp/gates/__init__.py
mpqp/local_storage/__init__.py
mpqp/local_storage/delete.py
mpqp/local_storage/load.py
mpqp/local_storage/queries.py
mpqp/local_storage/save.py
mpqp/local_storage/setup.py
mpqp/measures/__init__.py
mpqp-0.5.0.dist-info/licenses/LICENSE
mpqp-0.5.0.dist-info/METADATA
mpqp-0.5.0.dist-info/WHEEL
mpqp-0.5.0.dist-info/entry_points.txt
mpqp-0.5.0.dist-info/top_level.txt
mpqp-0.5.0.dist-info/RECORD
