Metadata-Version: 2.4
Name: mpqp
Version: 0.5.0
Summary: Facilitate quantum algorithm development and execution, regardless of the hardware, with MPQP
Home-page: https://colibritd.com
Author: ColibriTD
Author-email: quantum@colibritd.com
License: GPL-3.0-or-later
Project-URL: Repository, https://github.com/ColibrITD-SAS/mpqp
Project-URL: Documentation, https://mpqpdoc.colibri-quantum.com/
Project-URL: License, https://github.com/ColibrITD-SAS/mpqp/blob/main/LICENSE
Project-URL: Company, https://colibritd.com
Classifier: License :: OSI Approved :: GNU General Public License v3 or later (GPLv3+)
License-File: LICENSE
Requires-Dist: wheel
Requires-Dist: numpy>=1.26.4
Requires-Dist: scipy>=1.11.4
Requires-Dist: amazon-braket-sdk==1.79.1
Requires-Dist: aws-configure==2.1.8
Requires-Dist: boto3==1.35.82
Requires-Dist: osqp==1.0.1
Requires-Dist: amazon-braket-default-simulator==1.23.2
Requires-Dist: myqlm==1.10.6
Requires-Dist: myqlm-interop
Requires-Dist: cvxpy==1.4.3
Requires-Dist: qiskit==1.2.4
Requires-Dist: qiskit-ibm-runtime==0.31.0
Requires-Dist: qiskit-aer==0.15.1
Requires-Dist: azure-quantum==3.1.0
Requires-Dist: azure-quantum[qiskit]
Requires-Dist: python_dotenv>=1.0.0
Requires-Dist: jsonschema>=4.17.3
Requires-Dist: typeguard>=4.2.1
Requires-Dist: pylatexenc==2.10
Requires-Dist: anytree>=2.12.1
Requires-Dist: sympy==1.13.1
Requires-Dist: pick==2.2.0
Requires-Dist: termcolor==2.4.0
Requires-Dist: aenum==3.1.15
Requires-Dist: symengine>=0.11.0
Requires-Dist: cirq-core==1.3.0
Requires-Dist: qsimcirq
Requires-Dist: cirq-google==1.3.0
Requires-Dist: cirq-ionq==1.3.0
Requires-Dist: cirq-aqt==1.3.0
Requires-Dist: numba==0.60.0
Dynamic: author
Dynamic: author-email
Dynamic: classifier
Dynamic: description
Dynamic: description-content-type
Dynamic: home-page
Dynamic: license
Dynamic: license-file
Dynamic: project-url
Dynamic: requires-dist
Dynamic: summary
